Metadata-Version: 2.1
Name: pydocument
Version: 1.0
Summary: Easy way to make documents with gui (tkinter)
Home-page: UNKNOWN
Author: Jack Murrow
Author-email: jack.murrow122005@gmail.com
License: UNLICENSED
Keywords: PyDocument,Python Document,Document
Platform: UNKNOWN
Classifier: Programming Language :: Python :: 3
